FFD/FFD.v
module FFD1 (input wire D1, enabled, clk, reset, output reg Q1);
always @(posedge clk or posedge enabled or posedge reset) begin

  if (reset)
    Q1<=0;
  else if (enabled)
    Q1<=D1;
  end
endmodule

module FFD2 (input wire [1:0]D2, input wire enabled, clk, reset, output wire [1:0]Q2);

FFD1 M1 (D2[0], enabled, clk, reset, Q2[0]);
FFD1 M2 (D2[1], enabled, clk, reset, Q2[1]);

endmodule

module FFD3 (input wire [3:0]D3, input wire enabled, clk, reset, output wire [3:0]Q3);

FFD1 M3 (D3[0], enabled, clk, reset, Q3[0]);
FFD1 M4 (D3[1], enabled, clk, reset, Q3[1]);
FFD1 M5 (D3[2], enabled, clk, reset, Q3[2]);
FFD1 M6 (D3[3], enabled, clk, reset, Q3[3]);

endmodule

FFD/FFD_tb.v
module testbench ();
reg D1, enabled, clk, reset;
reg [1:0] D2;
wire [1:0] Q2;
reg [3:0] D3;
wire [3:0] Q3;
wire Q1;

FFD1 F1(D1, enabled, clk, reset, Q1);
FFD2 F2(D2, enabled, clk, reset, Q2);
FFD3 F3(D3, enabled, clk, reset, Q3);

always
#1 clk=~clk;

initial begin
  #1
  $display("FFD de un bit");
  $display("clk D Reset Enabled Q");
  $display("-------------");
  $monitor("%b  %b  %b   %b   %b", clk, D1, reset, enabled, Q1);

  #1 reset=1; clk=0; enabled=1; D1=0;
  #1 reset=0;
  #5 D1=1;
  #5 enabled=0; D1=0;
  #5 enabled=1;
end

initial begin
#18
$display("FFD de dos bits");
$display("clk D Reset Enabled Q");
$display("-------------");
$monitor("%b  %b  %b   %b   %b", clk, D2, reset, enabled, Q2);

  #1 reset=1; clk=0; enabled=1; D2=0;
  #1 reset=0;
  #5 D2=1;
  #5 enabled=0; D2=0;
  #5 enabled=1;
end

initial begin
#36
$display("FFD de dos bits");
$display("clk D Reset Enabled Q");
$display("-------------");
$monitor("%b  %b  %b   %b   %b", clk, D3, reset, enabled, Q3);

  #1 reset=1; clk=0; enabled=1; D3=0;
  #1 reset=0;
  #5 D3=1;
  #5 enabled=0; D3=0;
  #5 enabled=1;
end

initial
  #54 $finish;
initial begin
  $dumpfile("FFD_tb.vcd");
  $dumpvars(0, testbench);
end



endmodule

FFD/FFD_tb.vcd
$date
	Fri Oct 30 19:44:46 2020
$end
$version
	Icarus Verilog
$end
$timescale
	1ps
$end
$scope module testbench $end
$var wire 4 ! Q3 [3:0] $end
$var wire 2 " Q2 [1:0] $end
$var wire 1 # Q1 $end
$var reg 1 $ D1 $end
$var reg 2 % D2 [1:0] $end
$var reg 4 & D3 [3:0] $end
$var reg 1 ' clk $end
$var reg 1 ( enabled $end
$var reg 1 ) reset $end
$scope module F1 $end
$var wire 1 $ D1 $end
$var wire 1 ' clk $end
$var wire 1 ( enabled $end
$var wire 1 ) reset $end
$var reg 1 # Q1 $end
$upscope $end
$scope module F2 $end
$var wire 2 * D2 [1:0] $end
$var wire 1 ' clk $end
$var wire 1 ( enabled $end
$var wire 1 ) reset $end
$var wire 2 + Q2 [1:0] $end
$scope module M1 $end
$var wire 1 , D1 $end
$var wire 1 ' clk $end
$var wire 1 ( enabled $end
$var wire 1 ) reset $end
$var reg 1 - Q1 $end
$upscope $end
$scope module M2 $end
$var wire 1 . D1 $end
$var wire 1 ' clk $end
$var wire 1 ( enabled $end
$var wire 1 ) reset $end
$var reg 1 / Q1 $end
$upscope $end
$upscope $end
$scope module F3 $end
$var wire 4 0 D3 [3:0] $end
$var wire 1 ' clk $end
$var wire 1 ( enabled $end
$var wire 1 ) reset $end
$var wire 4 1 Q3 [3:0] $end
$scope module M3 $end
$var wire 1 2 D1 $end
$var wire 1 ' clk $end
$var wire 1 ( enabled $end
$var wire 1 ) reset $end
$var reg 1 3 Q1 $end
$upscope $end
$scope module M4 $end
$var wire 1 4 D1 $end
$var wire 1 ' clk $end
$var wire 1 ( enabled $end
$var wire 1 ) reset $end
$var reg 1 5 Q1 $end
$upscope $end
$scope module M5 $end
$var wire 1 6 D1 $end
$var wire 1 ' clk $end
$var wire 1 ( enabled $end
$var wire 1 ) reset $end
$var reg 1 7 Q1 $end
$upscope $end
$scope module M6 $end
$var wire 1 8 D1 $end
$var wire 1 ' clk $end
$var wire 1 ( enabled $end
$var wire 1 ) reset $end
$var reg 1 9 Q1 $end
$upscope $end
$upscope $end
$upscope $end
$enddefinitions $end
#0
$dumpvars
x9
x8
x7
x6
x5
x4
x3
x2
bx 1
bx 0
x/
x.
x-
x,
bx +
bx *
x)
x(
x'
bx &
bx %
x$
x#
bx "
bx !
$end
#2
0#
0-
b0 "
b0 +
0/
03
05
07
b0 !
b0 1
09
0$
1(
0'
1)
#3
x9
x7
x5
bx !
bx 1
x3
x/
bx "
bx +
x-
0)
1'
#4
0'
#5
1'
#6
0'
#7
1'
#8
0'
1$
#9
1#
1'
#10
0'
#11
1'
#12
0'
#13
1'
0$
0(
#14
0'
#15
1'
#16
0'
#17
1'
#18
0#
0'
1(
#19
0-
b0 "
b0 +
0/
03
05
07
b0 !
b0 1
09
0,
0.
1'
b0 %
b0 *
1)
#20
0'
0)
#21
x9
x7
x5
bx !
bx 1
x3
1'
#22
0'
#23
1'
#24
0'
#25
b1 "
b1 +
1-
1,
1'
b1 %
b1 *
#26
0'
#27
1'
#28
0'
#29
1'
#30
0,
0'
b0 %
b0 *
0(
#31
1'
#32
0'
#33
1'
#34
0'
#35
b0 "
b0 +
0-
1'
1(
#36
0'
#37
09
07
05
b0 !
b0 1
03
02
04
06
08
1'
b0 &
b0 0
1)
#38
0'
0)
#39
1'
#40
0'
#41
1'
#42
0'
#43
b1 !
b1 1
13
12
1'
b1 &
b1 0
#44
0'
#45
1'
#46
0'
#47
1'
#48
02
0'
b0 &
b0 0
0(
#49
1'
#50
0'
#51
1'
#52
0'
#53
b0 !
b0 1
03
1'
1(
